icecore/__init__.py
icecore/icecore.so
icecore/libICECrypt.so.1.0
icecore/libcryptopp.so.6.0
ice_icecore-1.0.2.dist-info/METADATA
ice_icecore-1.0.2.dist-info/WHEEL
ice_icecore-1.0.2.dist-info/top_level.txt
ice_icecore-1.0.2.dist-info/RECORD
